atomsciml-0.0.0.dist-info/top_level.txt
atomsciml-0.0.0.dist-info/WHEEL
atomsciml-0.0.0.dist-info/entry_points.txt
atomsciml-0.0.0.dist-info/LICENSE
atomsciml-0.0.0.dist-info/METADATA
atomsciml-0.0.0.dist-info/RECORD
atomsciml.libs/libsuperlu-1dbb25ff.so.5.1
atomsciml.libs/libtatlas-6cc7999c.so.3.10
atomsciml.libs/liblapack-1ad85175.so.3.4.2
atomsciml.libs/libgomp-a34b3233.so.1.0.0
atomsciml.libs/libarpack-7b0c1a60.so.2.0.0
atomsciml.libs/libarmadillo-23f68ba9.so.8.600.1
atomsciml.libs/libquadmath-96973f99.so.0.0.0
atomsciml.libs/libsz-fcfb8163.so.2.0.1
atomsciml.libs/libaec-dda3378b.so.0.0.10
atomsciml.libs/libgfortran-91cc3cb1.so.3.0.0
atomsciml.libs/libsatlas-7e2f78d2.so.3.10
atomsciml.libs/libhdf5-31426894.so.8.0.1
atomsciml.libs/libopenblaso-r0-70c28697.3.3.so
atomsciml.libs/libblas-357956a1.so.3.4.2
atomsciml/__init__.py
atomsciml/cmd/__init__.py
atomsciml/cmd/atomsciml.py
atomsciml/cpp/utils.cpython-310-x86_64-linux-gnu.so
atomsciml/cpp/__init__.py
atomsciml/electrondensity/__init__.py
atomsciml/electrondensity/ed2mdpot.py
atomsciml/electrondensity/electrondensity.py
