Metadata-Version: 2.1
Name: atomsciml
Version: 0.0.0
Summary: machine learning environment for scientific research involving atom.
Home-page: https://gitlab.com/deqitang/atomsciml
Author-email: deqi_tang@163.com
License: MIT
Keywords: Atom Science,Machine Learning
Platform: any
Requires-Python: >=3.0
License-File: LICENSE
Requires-Dist: pybind11
Requires-Dist: numpy
Requires-Dist: scipy
Requires-Dist: matplotlib
